odoo/addons/web_view_calendar_column/README.rst
odoo/addons/web_view_calendar_column/__init__.py
odoo/addons/web_view_calendar_column/__manifest__.py
odoo/addons/web_view_calendar_column/i18n/fr.po
odoo/addons/web_view_calendar_column/i18n/pt_BR.po
odoo/addons/web_view_calendar_column/i18n/web_view_calendar_column.pot
odoo/addons/web_view_calendar_column/readme/CONTRIBUTORS.rst
odoo/addons/web_view_calendar_column/readme/DESCRIPTION.rst
odoo/addons/web_view_calendar_column/readme/USAGE.rst
odoo/addons/web_view_calendar_column/static/description/icon.png
odoo/addons/web_view_calendar_column/static/description/index.html
odoo/addons/web_view_calendar_column/static/lib/scheduler.min.css
odoo/addons/web_view_calendar_column/static/lib/scheduler.min.js
odoo/addons/web_view_calendar_column/static/src/js/calendar_controller.js
odoo/addons/web_view_calendar_column/static/src/js/calendar_model.js
odoo/addons/web_view_calendar_column/static/src/js/calendar_renderer.js
odoo/addons/web_view_calendar_column/static/src/js/calendar_view.js
odoo/addons/web_view_calendar_column/views/assets.xml
odoo12_addon_web_view_calendar_column-12.0.1.0.0.99.dev9.dist-info/METADATA
odoo12_addon_web_view_calendar_column-12.0.1.0.0.99.dev9.dist-info/WHEEL
odoo12_addon_web_view_calendar_column-12.0.1.0.0.99.dev9.dist-info/top_level.txt
odoo12_addon_web_view_calendar_column-12.0.1.0.0.99.dev9.dist-info/RECORD
